mcp_nvd/__init__.py
mcp_nvd/client.py
mcp_nvd/main.py
mcp_nvd/server.py
mcp_nvd-0.0.1.dist-info/METADATA
mcp_nvd-0.0.1.dist-info/WHEEL
mcp_nvd-0.0.1.dist-info/entry_points.txt
mcp_nvd-0.0.1.dist-info/licenses/LICENSE
mcp_nvd-0.0.1.dist-info/RECORD
