Metadata-Version: 2.4
Name: mcp-nvd
Version: 0.0.1
Summary: An MCP server to interact with a the NVD Database API.
Author: Graziano Labs Corp.
Maintainer-email: Marco Graziano <marco@graziano.com>
License: MIT
License-File: LICENSE
Keywords: cybersecurity,llm,mcp
Requires-Python: >=3.10
Requires-Dist: httpx>=0.27.2
Requires-Dist: mcp>=1.0.0
Requires-Dist: python-dotenv>=1.0.1
Requires-Dist: starlette>=0.36.0
Requires-Dist: typer>=0.15.2
Requires-Dist: uvicorn>=0.27.0
